lupin2/__init__.py
lupin2/ml.py
lupin2/plt.py
lupin2/tools.py
lupin2-0.0.34.dist-info/METADATA
lupin2-0.0.34.dist-info/WHEEL
lupin2-0.0.34.dist-info/top_level.txt
lupin2-0.0.34.dist-info/RECORD
