Metadata-Version: 2.1
Name: lupin2
Version: 0.0.34
Summary: for myself
Home-page: https://github.com/RoRyou/Lupin2
Author: Roryou
Author-email: rokira0825@outlook.com
Classifier: Programming Language :: Python :: 3
Classifier: License :: OSI Approved :: MIT License
Classifier: Operating System :: OS Independent
